{
  "id": "LCR 100",
  "title": "三角形最小路径和",
  "titleSlug": "IlPe0q",
  "difficulty": "Medium",
  "category": "Algorithms",
  "topics": [
    "Array",
    "Dynamic Programming"
  ],
  "content": "<p>English description is not available for the problem. Please switch to Chinese.</p>\n",
  "codeSnippets": {
    "cpp": "class Solution {\npublic:\n    int minimumTotal(vector<vector<int>>& triangle) {\n\n    }\n};",
    "java": "class Solution {\n    public int minimumTotal(List<List<Integer>> triangle) {\n\n    }\n}",
    "python": "class Solution(object):\n    def minimumTotal(self, triangle):\n        \"\"\"\n        :type triangle: List[List[int]]\n        :rtype: int\n        \"\"\"",
    "python3": "class Solution:\n    def minimumTotal(self, triangle: List[List[int]]) -> int:",
    "c": "\n\nint minimumTotal(int** triangle, int triangleSize, int* triangleColSize){\n\n}",
    "csharp": "public class Solution {\n    public int MinimumTotal(IList<IList<int>> triangle) {\n\n    }\n}",
    "javascript": "/**\n * @param {number[][]} triangle\n * @return {number}\n */\nvar minimumTotal = function(triangle) {\n\n};",
    "typescript": "function minimumTotal(triangle: number[][]): number {\n\n};",
    "php": "class Solution {\n\n    /**\n     * @param Integer[][] $triangle\n     * @return Integer\n     */\n    function minimumTotal($triangle) {\n\n    }\n}",
    "swift": "class Solution {\n    func minimumTotal(_ triangle: [[Int]]) -> Int {\n\n    }\n}",
    "kotlin": "class Solution {\n    fun minimumTotal(triangle: List<List<Int>>): Int {\n\n    }\n}",
    "golang": "func minimumTotal(triangle [][]int) int {\n\n}",
    "ruby": "# @param {Integer[][]} triangle\n# @return {Integer}\ndef minimum_total(triangle)\n\nend",
    "scala": "object Solution {\n    def minimumTotal(triangle: List[List[Int]]): Int = {\n\n    }\n}",
    "rust": "impl Solution {\n    pub fn minimum_total(triangle: Vec<Vec<i32>>) -> i32 {\n\n    }\n}",
    "racket": "(define/contract (minimum-total triangle)\n  (-> (listof (listof exact-integer?)) exact-integer?)\n\n  )",
    "erlang": "-spec minimum_total(Triangle :: [[integer()]]) -> integer().\nminimum_total(Triangle) ->\n  .",
    "elixir": "defmodule Solution do\n  @spec minimum_total(triangle :: [[integer]]) :: integer\n  def minimum_total(triangle) do\n\n  end\nend"
  },
  "exampleTestcases": "[[2],[3,4],[6,5,7],[4,1,8,3]]\n[[-10]]",
  "hints": []
}